pydal_rqlite/__about__.py
pydal_rqlite/__init__.py
pydal_rqlite/adapter_rqlite.py
pydal_rqlite-0.1.0.dist-info/METADATA
pydal_rqlite-0.1.0.dist-info/WHEEL
pydal_rqlite-0.1.0.dist-info/RECORD
