Metadata-Version: 2.3
Name: pydal-rqlite
Version: 0.1.0
Summary: Custom pyDAL adapter for rqlite (distributed SQLite)
Project-URL: Homepage, https://github.com/educationwarehouse/pydal-adapter-rqlite
Author-email: Robin van der Noord <robin.vdn@educationwarehouse.nl>
Requires-Python: >=3.10
Requires-Dist: pydal
Requires-Dist: pyrqlite
Provides-Extra: dev
Requires-Dist: hatch; extra == 'dev'
Requires-Dist: python-semantic-release<8; extra == 'dev'
